chipsff/__init__.py
chipsff/alignn_ff_db_analyzer.py
chipsff/calcs.py
chipsff/config.py
chipsff/error_metrics.py
chipsff/general_material_analyzer.py
chipsff/mlearn_db_analyzer.py
chipsff/mptraj_analyzer.py
chipsff/run_chipsff.py
chipsff/scaling_analyzer.py
chipsff/utils.py
chipsff-2024.11.30.dist-info/LICENSE
chipsff-2024.11.30.dist-info/METADATA
chipsff-2024.11.30.dist-info/WHEEL
chipsff-2024.11.30.dist-info/entry_points.txt
chipsff-2024.11.30.dist-info/top_level.txt
chipsff-2024.11.30.dist-info/RECORD
